launchpadtools/__about__.py
launchpadtools/__init__.py
launchpadtools/cli.py
launchpadtools/submit.py
launchpadtools-0.7.1.dist-info/METADATA
launchpadtools-0.7.1.dist-info/WHEEL
launchpadtools-0.7.1.dist-info/entry_points.txt
launchpadtools-0.7.1.dist-info/top_level.txt
launchpadtools-0.7.1.dist-info/RECORD
