Metadata-Version: 2.1
Name: launchpadtools
Version: 0.7.1
Summary: Tools for submitting packages to Ubuntu Launchpad
Home-page: https://github.com/nschloe/launchpadtools
Author: Nico Schlömer
Author-email: nico.schloemer@gmail.com
License: License :: OSI Approved :: MIT License
Platform: any
Classifier: Development Status :: 4 - Beta
Classifier: License :: OSI Approved :: MIT License
Classifier: Intended Audience :: Developers
Classifier: Operating System :: OS Independent
Classifier: Programming Language :: Python
Classifier: Programming Language :: Python :: 3
Classifier: Topic :: Software Development :: Build Tools
Classifier: Topic :: System :: Operating System
Requires-Dist: GitPython
Requires-Dist: launchpadlib
Requires-Dist: paramiko
